{"ticker":"ES","schema_version":"2.1.0","current":{"signal":null,"signal_source":null,"signal_started_date":null,"signal_trading_days":null,"position_strength":null,"peak_gain_pct":null},"metrics":{"trade_count":8,"avg_hold_days":13.2,"avg_gain_pct":0.5372,"avg_peak_gain_pct":3.8112,"success_rate":0.5},"history":[{"date":"2025-04-23","close":57.96,"volume":2170700,"signal":null,"psar":52.8079},{"date":"2025-04-24","close":58.53,"volume":2286300,"signal":null,"psar":53.0628},{"date":"2025-04-25","close":57.86,"volume":2992200,"signal":null,"psar":53.3075},{"date":"2025-04-28","close":59.1,"volume":7427600,"signal":null,"psar":53.5424},{"date":"2025-04-29","close":59.42,"volume":4396300,"signal":null,"psar":53.8902},{"date":"2025-04-30","close":59.48,"volume":5246000,"signal":null,"psar":54.3478},{"date":"2025-05-01","close":59.08,"volume":2793700,"signal":null,"psar":54.915},{"date":"2025-05-02","close":58.83,"volume":3877400,"signal":null,"psar":55.4255},{"date":"2025-05-05","close":59.29,"volume":2067300,"signal":null,"psar":55.885},{"date":"2025-05-06","close":59.21,"volume":2492200,"signal":null,"psar":56.2985},{"date":"2025-05-07","close":62.24,"volume":4553700,"signal":null,"psar":56.6706},{"date":"2025-05-08","close":62.71,"volume":2973100,"signal":null,"psar":57.411},{"date":"2025-05-09","close":63.0,"volume":2341100,"signal":null,"psar":58.2466},{"date":"2025-05-12","close":62.25,"volume":2201000,"signal":null,"psar":58.9653},{"date":"2025-05-13","close":62.91,"volume":2705700,"signal":null,"psar":59.5834},{"date":"2025-05-14","close":61.35,"volume":2670000,"signal":null,"psar":60.2116},{"date":"2025-05-15","close":62.38,"volume":2942700,"signal":null,"psar":60.62},{"date":"2025-05-16","close":63.2,"volume":2129300,"signal":null,"psar":60.62},{"date":"2025-05-19","close":63.53,"volume":1887700,"signal":null,"psar":60.75},{"date":"2025-05-20","close":65.55,"volume":3665800,"signal":null,"psar":61.2648},{"date":"2025-05-21","close":63.96,"volume":2674600,"signal":null,"psar":62.2438},{"date":"2025-05-22","close":63.06,"volume":1949100,"signal":null,"psar":66.16},{"date":"2025-05-23","close":63.46,"volume":1587300,"signal":null,"psar":66.0828},{"date":"2025-05-27","close":64.61,"volume":2260000,"signal":"SELL","psar":65.9283},{"date":"2025-05-28","close":63.37,"volume":1692800,"signal":"SELL","psar":65.78},{"date":"2025-05-29","close":64.09,"volume":1766600,"signal":"SELL","psar":65.6376},{"date":"2025-05-30","close":64.81,"volume":5660700,"signal":"SELL","psar":65.5009},{"date":"2025-06-02","close":64.92,"volume":1775300,"signal":"SELL","psar":65.3696},{"date":"2025-06-03","close":65.25,"volume":2928000,"signal":"BUY","psar":62.22},{"date":"2025-06-04","close":64.66,"volume":2981100,"signal":"BUY","psar":62.284},{"date":"2025-06-05","close":65.3,"volume":4307200,"signal":"BUY","psar":62.4106},{"date":"2025-06-06","close":65.49,"volume":2738500,"signal":"BUY","psar":62.6086},{"date":"2025-06-09","close":65.64,"volume":1840300,"signal":"BUY","psar":62.7947},{"date":"2025-06-10","close":65.89,"volume":2142200,"signal":"BUY","psar":63.0703},{"date":"2025-06-11","close":65.55,"volume":1393700,"signal":"BUY","psar":63.3239},{"date":"2025-06-12","close":65.8,"volume":1634400,"signal":"BUY","psar":63.5572},{"date":"2025-06-13","close":65.21,"volume":1750700,"signal":"BUY","psar":63.7718},{"date":"2025-06-16","close":64.36,"volume":1934300,"signal":"BUY","psar":63.9693},{"date":"2025-06-17","close":63.2,"volume":2568000,"signal":null,"psar":66.24},{"date":"2025-06-18","close":62.4,"volume":2799300,"signal":null,"psar":66.174},{"date":"2025-06-20","close":62.52,"volume":5066300,"signal":null,"psar":66.0214},{"date":"2025-06-23","close":63.37,"volume":3175600,"signal":null,"psar":65.7976},{"date":"2025-06-24","close":63.84,"volume":2793800,"signal":null,"psar":65.5871},{"date":"2025-06-25","close":62.46,"volume":2292900,"signal":null,"psar":65.3893},{"date":"2025-06-26","close":63.25,"volume":2389500,"signal":null,"psar":65.2033},{"date":"2025-06-27","close":63.36,"volume":2858700,"signal":null,"psar":65.0285},{"date":"2025-06-30","close":63.62,"volume":4386100,"signal":null,"psar":64.8642},{"date":"2025-07-01","close":64.55,"volume":2135200,"signal":null,"psar":61.88},{"date":"2025-07-02","close":64.45,"volume":1855900,"signal":null,"psar":61.88},{"date":"2025-07-03","close":64.55,"volume":1471300,"signal":null,"psar":61.9448},{"date":"2025-07-07","close":64.39,"volume":1781400,"signal":null,"psar":62.0083},{"date":"2025-07-08","close":64.56,"volume":2257400,"signal":null,"psar":62.0705},{"date":"2025-07-09","close":65.11,"volume":1972000,"signal":null,"psar":62.1315},{"date":"2025-07-10","close":66.11,"volume":1484600,"signal":null,"psar":62.2519},{"date":"2025-07-11","close":65.71,"volume":1605800,"signal":null,"psar":62.4846},{"date":"2025-07-14","close":65.38,"volume":2174200,"signal":null,"psar":62.7033},{"date":"2025-07-15","close":64.72,"volume":1479700,"signal":null,"psar":62.9822},{"date":"2025-07-16","close":64.79,"volume":1962700,"signal":null,"psar":63.2388},{"date":"2025-07-17","close":64.84,"volume":2106400,"signal":null,"psar":63.4749},{"date":"2025-07-18","close":65.41,"volume":3868800,"signal":null,"psar":63.6921},{"date":"2025-07-21","close":65.54,"volume":1379200,"signal":null,"psar":63.892},{"date":"2025-07-22","close":66.61,"volume":1591800,"signal":null,"psar":64.0758},{"date":"2025-07-23","close":66.37,"volume":1599700,"signal":null,"psar":64.3362},{"date":"2025-07-24","close":66.41,"volume":1594300,"signal":null,"psar":64.6415},{"date":"2025-07-25","close":66.62,"volume":1715900,"signal":null,"psar":64.9101},{"date":"2025-07-28","close":65.18,"volume":1695100,"signal":null,"psar":66.88},{"date":"2025-07-29","close":66.37,"volume":1848900,"signal":"SELL","psar":66.842},{"date":"2025-07-30","close":65.99,"volume":1859300,"signal":"BUY","psar":64.98},{"date":"2025-07-31","close":66.1,"volume":4534200,"signal":"BUY","psar":65.017},{"date":"2025-08-01","close":65.55,"volume":2841200,"signal":"BUY","psar":65.0533},{"date":"2025-08-04","close":66.46,"volume":2027800,"signal":"BUY","psar":65.0888},{"date":"2025-08-05","close":65.88,"volume":1606900,"signal":"BUY","psar":65.1236},{"date":"2025-08-06","close":65.43,"volume":1982700,"signal":"BUY","psar":65.2023},{"date":"2025-08-07","close":65.93,"volume":1692800,"signal":"BUY","psar":65.2778},{"date":"2025-08-08","close":65.04,"volume":2162500,"signal":null,"psar":67.09},{"date":"2025-08-11","close":65.69,"volume":2163300,"signal":null,"psar":67.04},{"date":"2025-08-12","close":65.82,"volume":1784100,"signal":null,"psar":66.991},{"date":"2025-08-13","close":66.3,"volume":1432300,"signal":null,"psar":66.943},{"date":"2025-08-14","close":65.51,"volume":2176900,"signal":null,"psar":66.8959},{"date":"2025-08-15","close":65.53,"volume":2314000,"signal":null,"psar":66.8498},{"date":"2025-08-18","close":64.54,"volume":1924400,"signal":null,"psar":66.8046},{"date":"2025-08-19","close":65.71,"volume":1375900,"signal":null,"psar":66.708},{"date":"2025-08-20","close":65.71,"volume":1853000,"signal":null,"psar":64.39},{"date":"2025-08-21","close":65.42,"volume":1456400,"signal":null,"psar":64.4452},{"date":"2025-08-22","close":66.53,"volume":1528800,"signal":null,"psar":64.4993},{"date":"2025-08-25","close":63.39,"volume":6013500,"signal":null,"psar":67.15},{"date":"2025-08-26","close":64.11,"volume":5334600,"signal":null,"psar":67.0376},{"date":"2025-08-27","close":64.8,"volume":2512700,"signal":null,"psar":66.9274},{"date":"2025-08-28","close":64.3,"volume":1886900,"signal":null,"psar":66.8195},{"date":"2025-08-29","close":64.07,"volume":1740700,"signal":null,"psar":66.7137},{"date":"2025-09-02","close":63.7,"volume":1780300,"signal":null,"psar":66.61},{"date":"2025-09-03","close":63.3,"volume":1944700,"signal":null,"psar":66.5084},{"date":"2025-09-04","close":63.42,"volume":2336900,"signal":null,"psar":66.4089},{"date":"2025-09-05","close":63.53,"volume":1653300,"signal":null,"psar":66.3113},{"date":"2025-09-08","close":62.86,"volume":2591000,"signal":null,"psar":66.2157},{"date":"2025-09-09","close":63.88,"volume":3149300,"signal":null,"psar":66.1219},{"date":"2025-09-10","close":64.01,"volume":3130300,"signal":null,"psar":66.0301},{"date":"2025-09-11","close":65.05,"volume":2725500,"signal":null,"psar":65.9401},{"date":"2025-09-12","close":65.7,"volume":2168900,"signal":null,"psar":65.8519},{"date":"2025-09-15","close":65.52,"volume":2869600,"signal":null,"psar":61.53},{"date":"2025-09-16","close":63.42,"volume":2994500,"signal":null,"psar":61.6242},{"date":"2025-09-17","close":63.3,"volume":2604100,"signal":null,"psar":61.7165},{"date":"2025-09-18","close":63.88,"volume":3176700,"signal":null,"psar":61.807},{"date":"2025-09-19","close":67.0,"volume":13697800,"signal":null,"psar":61.8956},{"date":"2025-09-22","close":67.66,"volume":6796700,"signal":null,"psar":62.1986},{"date":"2025-09-23","close":69.42,"volume":3831200,"signal":null,"psar":62.4895},{"date":"2025-09-24","close":69.1,"volume":3835400,"signal":null,"psar":62.7687},{"date":"2025-09-25","close":68.5,"volume":3175500,"signal":null,"psar":63.181},{"date":"2025-09-26","close":69.77,"volume":3139200,"signal":null,"psar":63.5685},{"date":"2025-09-29","close":70.53,"volume":2462500,"signal":null,"psar":64.0806},{"date":"2025-09-30","close":71.14,"volume":2599100,"signal":null,"psar":64.7376},{"date":"2025-10-01","close":71.6,"volume":3624600,"signal":null,"psar":65.5095},{"date":"2025-10-02","close":71.79,"volume":2994300,"signal":null,"psar":66.4167},{"date":"2025-10-03","close":72.53,"volume":2659200,"signal":null,"psar":67.197},{"date":"2025-10-06","close":72.7,"volume":2719500,"signal":null,"psar":68.2023},{"date":"2025-10-07","close":72.84,"volume":3379900,"signal":null,"psar":69.0467},{"date":"2025-10-08","close":73.49,"volume":2916500,"signal":null,"psar":69.756},{"date":"2025-10-09","close":72.39,"volume":1771000,"signal":null,"psar":70.6028},{"date":"2025-10-10","close":72.35,"volume":1459100,"signal":null,"psar":71.2971},{"date":"2025-10-13","close":70.97,"volume":2970700,"signal":null,"psar":74.46},{"date":"2025-10-14","close":70.59,"volume":2986800,"signal":null,"psar":74.3828},{"date":"2025-10-15","close":72.24,"volume":2094300,"signal":null,"psar":74.2207},{"date":"2025-10-16","close":71.36,"volume":2116000,"signal":null,"psar":74.0651},{"date":"2025-10-17","close":72.56,"volume":2843500,"signal":null,"psar":73.9157},{"date":"2025-10-20","close":72.85,"volume":2344400,"signal":null,"psar":73.7722},{"date":"2025-10-21","close":73.21,"volume":2544100,"signal":"BUY","psar":70.33},{"date":"2025-10-22","close":73.12,"volume":2771800,"signal":"BUY","psar":70.4072},{"date":"2025-10-23","close":73.89,"volume":2336200,"signal":"BUY","psar":70.4829},{"date":"2025-10-24","close":74.67,"volume":1807300,"signal":"BUY","psar":70.557},{"date":"2025-10-27","close":74.71,"volume":1680400,"signal":"BUY","psar":70.7367},{"date":"2025-10-28","close":74.88,"volume":2287200,"signal":"BUY","psar":70.9093},{"date":"2025-10-29","close":73.81,"volume":1960800,"signal":"BUY","psar":71.1697},{"date":"2025-10-30","close":73.8,"volume":2358500,"signal":"BUY","psar":71.4145},{"date":"2025-10-31","close":73.81,"volume":3103700,"signal":"BUY","psar":71.6446},{"date":"2025-11-03","close":74.36,"volume":2638600,"signal":"BUY","psar":71.861},{"date":"2025-11-04","close":73.82,"volume":3406600,"signal":"BUY","psar":72.0643},{"date":"2025-11-05","close":72.91,"volume":3167800,"signal":null,"psar":75.25},{"date":"2025-11-06","close":71.54,"volume":2716800,"signal":null,"psar":75.1864},{"date":"2025-11-07","close":73.04,"volume":2701700,"signal":null,"psar":75.0249},{"date":"2025-11-10","close":72.51,"volume":2778600,"signal":null,"psar":74.8699},{"date":"2025-11-11","close":73.33,"volume":2591700,"signal":null,"psar":74.7211},{"date":"2025-11-12","close":73.61,"volume":2047300,"signal":null,"psar":74.5783},{"date":"2025-11-13","close":73.69,"volume":2142000,"signal":null,"psar":74.4412},{"date":"2025-11-14","close":73.3,"volume":2526800,"signal":null,"psar":74.3095},{"date":"2025-11-17","close":74.03,"volume":1804900,"signal":null,"psar":74.25},{"date":"2025-11-18","close":74.54,"volume":2710000,"signal":null,"psar":71.15},{"date":"2025-11-19","close":65.26,"volume":10405100,"signal":null,"psar":74.67},{"date":"2025-11-20","close":63.55,"volume":5818700,"signal":null,"psar":74.67},{"date":"2025-11-21","close":64.55,"volume":4206100,"signal":null,"psar":74.2212},{"date":"2025-11-24","close":65.68,"volume":4035300,"signal":null,"psar":73.7904},{"date":"2025-11-25","close":65.94,"volume":2356500,"signal":null,"psar":73.3767},{"date":"2025-11-26","close":66.7,"volume":1544000,"signal":null,"psar":72.9797},{"date":"2025-11-28","close":67.18,"volume":823300,"signal":null,"psar":72.5985},{"date":"2025-12-01","close":66.55,"volume":2547900,"signal":null,"psar":72.2325},{"date":"2025-12-02","close":66.31,"volume":1838500,"signal":null,"psar":71.8812},{"date":"2025-12-03","close":65.97,"volume":1854600,"signal":null,"psar":71.544},{"date":"2025-12-04","close":67.06,"volume":3493200,"signal":null,"psar":71.2202},{"date":"2025-12-05","close":66.74,"volume":2980000,"signal":null,"psar":70.9094},{"date":"2025-12-08","close":66.7,"volume":2668600,"signal":null,"psar":70.611},{"date":"2025-12-09","close":67.83,"volume":3521000,"signal":null,"psar":70.3246},{"date":"2025-12-10","close":67.63,"volume":2504700,"signal":null,"psar":70.0496},{"date":"2025-12-11","close":67.5,"volume":1591800,"signal":null,"psar":69.7856},{"date":"2025-12-12","close":68.11,"volume":1766500,"signal":null,"psar":69.5322},{"date":"2025-12-15","close":68.37,"volume":2583900,"signal":null,"psar":69.2889},{"date":"2025-12-16","close":67.89,"volume":2496700,"signal":null,"psar":69.0554},{"date":"2025-12-17","close":67.28,"volume":3231600,"signal":null,"psar":68.8311},{"date":"2025-12-18","close":67.98,"volume":2307000,"signal":null,"psar":68.78},{"date":"2025-12-19","close":67.16,"volume":4984100,"signal":null,"psar":68.5668},{"date":"2025-12-22","close":66.04,"volume":4055700,"signal":null,"psar":68.3621},{"date":"2025-12-23","close":66.37,"volume":2114500,"signal":null,"psar":68.1656},{"date":"2025-12-24","close":67.16,"volume":844300,"signal":null,"psar":67.977},{"date":"2025-12-26","close":67.24,"volume":876300,"signal":null,"psar":67.7959},{"date":"2025-12-29","close":67.2,"volume":1644900,"signal":null,"psar":63.45},{"date":"2025-12-30","close":67.55,"volume":1595100,"signal":null,"psar":63.5392},{"date":"2025-12-31","close":67.33,"volume":1564100,"signal":null,"psar":63.7156},{"date":"2026-01-02","close":68.06,"volume":1269300,"signal":null,"psar":63.885},{"date":"2026-01-05","close":67.05,"volume":2447000,"signal":null,"psar":64.1577},{"date":"2026-01-06","close":67.41,"volume":2156300,"signal":null,"psar":64.414},{"date":"2026-01-07","close":65.62,"volume":1768300,"signal":null,"psar":64.655},{"date":"2026-01-08","close":67.62,"volume":2692500,"signal":null,"psar":64.8815},{"date":"2026-01-09","close":67.79,"volume":2003400,"signal":null,"psar":65.0944},{"date":"2026-01-12","close":68.75,"volume":3226700,"signal":null,"psar":65.4093},{"date":"2026-01-13","close":68.4,"volume":1743500,"signal":null,"psar":65.7893},{"date":"2026-01-14","close":69.95,"volume":3043100,"signal":null,"psar":66.1314},{"date":"2026-01-15","close":69.69,"volume":2504100,"signal":null,"psar":66.6604},{"date":"2026-01-16","close":70.11,"volume":3203500,"signal":null,"psar":67.3184},{"date":"2026-01-20","close":70.79,"volume":2583700,"signal":null,"psar":67.8842},{"date":"2026-01-21","close":71.38,"volume":2016000,"signal":null,"psar":68.3708},{"date":"2026-01-22","close":70.45,"volume":1475300,"signal":null,"psar":68.8875},{"date":"2026-01-23","close":69.58,"volume":2441700,"signal":null,"psar":71.6},{"date":"2026-01-26","close":70.33,"volume":1587500,"signal":null,"psar":71.57},{"date":"2026-01-27","close":70.63,"volume":1928300,"signal":"SELL","psar":71.5162},{"date":"2026-01-28","close":69.9,"volume":3141700,"signal":"SELL","psar":71.4635},{"date":"2026-01-29","close":68.92,"volume":2967500,"signal":"SELL","psar":71.4118},{"date":"2026-01-30","close":69.13,"volume":3315600,"signal":"SELL","psar":71.38},{"date":"2026-02-02","close":67.91,"volume":3160700,"signal":"SELL","psar":71.1862},{"date":"2026-02-03","close":68.54,"volume":3142000,"signal":"SELL","psar":70.9113},{"date":"2026-02-04","close":68.24,"volume":3332200,"signal":"SELL","psar":70.6584},{"date":"2026-02-05","close":67.73,"volume":2548900,"signal":"SELL","psar":70.4257},{"date":"2026-02-06","close":67.36,"volume":3036800,"signal":"SELL","psar":70.1382},{"date":"2026-02-09","close":67.63,"volume":2612300,"signal":"SELL","psar":69.776},{"date":"2026-02-10","close":69.3,"volume":2323000,"signal":null,"psar":66.6},{"date":"2026-02-11","close":70.22,"volume":2739600,"signal":null,"psar":66.6},{"date":"2026-02-12","close":70.32,"volume":2810800,"signal":null,"psar":66.746},{"date":"2026-02-13","close":73.36,"volume":4279000,"signal":"BUY","psar":67.0348},{"date":"2026-02-17","close":73.03,"volume":4114800,"signal":"BUY","psar":67.6025},{"date":"2026-02-18","close":71.72,"volume":2263800,"signal":"BUY","psar":68.3422},{"date":"2026-02-19","close":73.67,"volume":2642100,"signal":"BUY","psar":69.008},{"date":"2026-02-20","close":73.56,"volume":4759600,"signal":"BUY","psar":69.6072},{"date":"2026-02-23","close":74.87,"volume":2455800,"signal":"BUY","psar":70.1465},{"date":"2026-02-24","close":75.13,"volume":2336800,"signal":"BUY","psar":70.6318},{"date":"2026-02-25","close":74.92,"volume":3188400,"signal":"BUY","psar":71.1896},{"date":"2026-02-26","close":75.05,"volume":1770000,"signal":"BUY","psar":71.6805},{"date":"2026-02-27","close":76.21,"volume":3171700,"signal":"BUY","psar":72.2054},{"date":"2026-03-02","close":74.42,"volume":2455100,"signal":"BUY","psar":72.8781},{"date":"2026-03-03","close":74.73,"volume":2083700,"signal":null,"psar":76.41},{"date":"2026-03-04","close":75.32,"volume":2337200,"signal":null,"psar":76.3284},{"date":"2026-03-05","close":73.87,"volume":2172900,"signal":"SELL","psar":76.2484},{"date":"2026-03-06","close":74.44,"volume":1938500,"signal":"SELL","psar":76.1701},{"date":"2026-03-09","close":73.85,"volume":2590509,"signal":"SELL","psar":76.0933},{"date":"2026-03-10","close":73.61,"volume":2038762,"signal":"SELL","psar":76.018},{"date":"2026-03-11","close":73.94,"volume":1433600,"signal":"SELL","psar":75.9442},{"date":"2026-03-12","close":73.21,"volume":1998100,"signal":"SELL","psar":75.872},{"date":"2026-03-13","close":73.1,"volume":2245000,"signal":"SELL","psar":75.8011},{"date":"2026-03-16","close":73.2,"volume":2699600,"signal":"SELL","psar":75.7317},{"date":"2026-03-17","close":72.44,"volume":2279200,"signal":"SELL","psar":75.5876},{"date":"2026-03-18","close":72.74,"volume":3029600,"signal":"SELL","psar":75.4493},{"date":"2026-03-19","close":69.62,"volume":4625800,"signal":"SELL","psar":75.2334},{"date":"2026-03-20","close":66.67,"volume":7240500,"signal":"SELL","psar":74.7691},{"date":"2026-03-23","close":67.65,"volume":2904000,"signal":"SELL","psar":73.9242},{"date":"2026-03-24","close":67.47,"volume":2693700,"signal":"SELL","psar":73.1638},{"date":"2026-03-25","close":67.04,"volume":3495600,"signal":"SELL","psar":72.4794},{"date":"2026-03-26","close":67.96,"volume":2015800,"signal":"SELL","psar":71.8634},{"date":"2026-03-27","close":67.59,"volume":2458100,"signal":"SELL","psar":71.3091},{"date":"2026-03-30","close":68.41,"volume":3025200,"signal":"SELL","psar":70.8102},{"date":"2026-03-31","close":69.28,"volume":3062600,"signal":"SELL","psar":70.3612},{"date":"2026-04-01","close":69.65,"volume":2467200,"signal":"SELL","psar":69.9571},{"date":"2026-04-02","close":69.47,"volume":2522800,"signal":null,"psar":66.32},{"date":"2026-04-06","close":69.44,"volume":1349900,"signal":null,"psar":66.3916},{"date":"2026-04-07","close":69.49,"volume":1345100,"signal":null,"psar":66.5395},{"date":"2026-04-08","close":69.95,"volume":2426900,"signal":null,"psar":66.6816},{"date":"2026-04-09","close":70.57,"volume":2614200,"signal":null,"psar":66.9023},{"date":"2026-04-10","close":69.97,"volume":2237200,"signal":null,"psar":67.2461},{"date":"2026-04-13","close":68.68,"volume":1913600,"signal":null,"psar":67.5624},{"date":"2026-04-14","close":69.01,"volume":1497700,"signal":null,"psar":67.8534},{"date":"2026-04-15","close":68.77,"volume":1919800,"signal":null,"psar":68.03},{"date":"2026-04-16","close":69.18,"volume":1478200,"signal":null,"psar":68.03},{"date":"2026-04-17","close":69.25,"volume":1650200,"signal":null,"psar":68.1},{"date":"2026-04-20","close":68.51,"volume":1328800,"signal":null,"psar":68.15},{"date":"2026-04-21","close":66.82,"volume":1636800,"signal":null,"psar":71.2},{"date":"2026-04-22","close":67.05,"volume":1454400,"signal":null,"psar":71.1122},{"date":"2026-04-23","close":68.77,"volume":1433100,"signal":null,"psar":71.0262},{"date":"2026-04-24","close":68.64,"volume":1655800,"signal":null,"psar":70.9418},{"date":"2026-04-27","close":68.72,"volume":1059104,"signal":null,"psar":70.8592},{"date":"2026-04-28","close":68.58,"volume":1617389,"signal":null,"psar":70.7782},{"date":"2026-04-29","close":68.72,"volume":1865550,"signal":null,"psar":70.6988},{"date":"2026-04-30","close":70.7,"volume":2763904,"signal":null,"psar":66.81},{"date":"2026-05-01","close":71.07,"volume":2149700,"signal":null,"psar":66.8958},{"date":"2026-05-04","close":69.44,"volume":1795791,"signal":null,"psar":67.0904},{"date":"2026-05-05","close":68.9,"volume":2000347,"signal":null,"psar":67.2772}]}