{"ticker":"PODD","schema_version":"2.1.0","current":{"signal":"SELL","signal_source":"secondary","signal_started_date":"2026-04-21","signal_trading_days":4,"position_strength":"Strong"},"metrics":{"trade_count":8,"avg_hold_days":15.0,"avg_gain_pct":-0.1905,"avg_peak_gain_pct":6.6124,"success_rate":0.5},"history":[{"date":"2025-04-14","close":255.47,"volume":538714,"signal":null,"psar":264.3078},{"date":"2025-04-15","close":256.425,"volume":542491,"signal":null,"psar":262.6513},{"date":"2025-04-16","close":250.73,"volume":731296,"signal":null,"psar":261.0943},{"date":"2025-04-17","close":246.8,"volume":623593,"signal":null,"psar":259.6306},{"date":"2025-04-21","close":238.57,"volume":518015,"signal":null,"psar":258.0},{"date":"2025-04-22","close":244.02,"volume":550609,"signal":null,"psar":256.0976},{"date":"2025-04-23","close":246.49,"volume":483849,"signal":null,"psar":234.22},{"date":"2025-04-24","close":259.38,"volume":520777,"signal":null,"psar":234.6506},{"date":"2025-04-25","close":260.71,"volume":465391,"signal":null,"psar":235.7294},{"date":"2025-04-28","close":259.52,"volume":766024,"signal":null,"psar":237.3557},{"date":"2025-04-29","close":251.27,"volume":1152369,"signal":null,"psar":239.5073},{"date":"2025-04-30","close":252.29,"volume":721003,"signal":null,"psar":241.4867},{"date":"2025-05-01","close":250.25,"volume":596730,"signal":null,"psar":243.3077},{"date":"2025-05-02","close":257.01,"volume":838691,"signal":null,"psar":244.9831},{"date":"2025-05-05","close":258.79,"volume":736896,"signal":null,"psar":246.5245},{"date":"2025-05-06","close":258.87,"volume":875585,"signal":null,"psar":247.9425},{"date":"2025-05-07","close":264.31,"volume":454907,"signal":null,"psar":249.2471},{"date":"2025-05-08","close":257.0,"volume":1284528,"signal":null,"psar":250.7894},{"date":"2025-05-09","close":310.67,"volume":3216236,"signal":null,"psar":252.7725},{"date":"2025-05-12","close":316.67,"volume":1404553,"signal":null,"psar":256.93},{"date":"2025-05-13","close":314.46,"volume":1469414,"signal":null,"psar":266.8391},{"date":"2025-05-14","close":321.41,"volume":966677,"signal":null,"psar":276.948},{"date":"2025-05-15","close":322.02,"volume":661127,"signal":null,"psar":285.2374},{"date":"2025-05-16","close":324.75,"volume":836440,"signal":null,"psar":292.0347},{"date":"2025-05-19","close":325.84,"volume":634501,"signal":null,"psar":298.6717},{"date":"2025-05-20","close":327.47,"volume":998439,"signal":null,"psar":304.2374},{"date":"2025-05-21","close":324.5,"volume":653398,"signal":null,"psar":309.1899},{"date":"2025-05-22","close":321.0,"volume":991446,"signal":null,"psar":313.2179},{"date":"2025-05-23","close":321.36,"volume":693225,"signal":null,"psar":329.33},{"date":"2025-05-27","close":326.64,"volume":697179,"signal":"BUY","psar":315.91},{"date":"2025-05-28","close":323.55,"volume":919852,"signal":"BUY","psar":315.91},{"date":"2025-05-29","close":323.85,"volume":427899,"signal":"BUY","psar":316.1738},{"date":"2025-05-30","close":325.03,"volume":960827,"signal":"BUY","psar":316.4324},{"date":"2025-06-02","close":325.0,"volume":712030,"signal":"BUY","psar":316.6858},{"date":"2025-06-03","close":323.24,"volume":859539,"signal":"BUY","psar":316.9341},{"date":"2025-06-04","close":319.21,"volume":789951,"signal":"BUY","psar":317.1775},{"date":"2025-06-05","close":317.16,"volume":902343,"signal":null,"psar":329.1018},{"date":"2025-06-06","close":311.77,"volume":682612,"signal":null,"psar":328.8302},{"date":"2025-06-09","close":305.66,"volume":912977,"signal":null,"psar":328.1194},{"date":"2025-06-10","close":298.73,"volume":1095681,"signal":null,"psar":326.5936},{"date":"2025-06-11","close":302.24,"volume":876549,"signal":null,"psar":324.1109},{"date":"2025-06-12","close":303.62,"volume":866112,"signal":null,"psar":321.8268},{"date":"2025-06-13","close":304.63,"volume":670639,"signal":null,"psar":319.7255},{"date":"2025-06-16","close":306.59,"volume":867353,"signal":null,"psar":317.7922},{"date":"2025-06-17","close":304.39,"volume":591849,"signal":null,"psar":316.0137},{"date":"2025-06-18","close":301.79,"volume":756476,"signal":null,"psar":314.3774},{"date":"2025-06-20","close":303.15,"volume":1539112,"signal":null,"psar":312.872},{"date":"2025-06-23","close":307.67,"volume":1171098,"signal":null,"psar":311.487},{"date":"2025-06-24","close":310.9,"volume":908070,"signal":null,"psar":295.56},{"date":"2025-06-25","close":306.23,"volume":639363,"signal":null,"psar":295.9586},{"date":"2025-06-26","close":309.83,"volume":628504,"signal":null,"psar":296.3492},{"date":"2025-06-27","close":313.08,"volume":760290,"signal":null,"psar":296.732},{"date":"2025-06-30","close":314.18,"volume":682904,"signal":null,"psar":297.1072},{"date":"2025-07-01","close":299.99,"volume":1404451,"signal":null,"psar":316.0},{"date":"2025-07-02","close":301.62,"volume":883997,"signal":null,"psar":316.0},{"date":"2025-07-03","close":301.05,"volume":527286,"signal":null,"psar":315.6094},{"date":"2025-07-07","close":300.7,"volume":585441,"signal":null,"psar":315.2266},{"date":"2025-07-08","close":296.51,"volume":714482,"signal":null,"psar":314.8515},{"date":"2025-07-09","close":297.46,"volume":456930,"signal":null,"psar":314.0646},{"date":"2025-07-10","close":297.4,"volume":475984,"signal":null,"psar":312.8237},{"date":"2025-07-11","close":289.32,"volume":507506,"signal":null,"psar":311.6572},{"date":"2025-07-14","close":292.01,"volume":605795,"signal":null,"psar":309.847},{"date":"2025-07-15","close":289.99,"volume":511058,"signal":null,"psar":308.1817},{"date":"2025-07-16","close":288.27,"volume":386917,"signal":null,"psar":306.6495},{"date":"2025-07-17","close":283.45,"volume":582258,"signal":null,"psar":304.7116},{"date":"2025-07-18","close":284.23,"volume":349138,"signal":null,"psar":302.0822},{"date":"2025-07-21","close":280.96,"volume":376478,"signal":null,"psar":299.7683},{"date":"2025-07-22","close":285.57,"volume":511230,"signal":null,"psar":297.0605},{"date":"2025-07-23","close":286.67,"volume":583597,"signal":null,"psar":294.7319},{"date":"2025-07-24","close":286.58,"volume":672088,"signal":null,"psar":292.7292},{"date":"2025-07-25","close":290.22,"volume":528141,"signal":"BUY","psar":280.427},{"date":"2025-07-28","close":292.27,"volume":397799,"signal":"BUY","psar":280.6433},{"date":"2025-07-29","close":291.49,"volume":373338,"signal":"BUY","psar":281.1817},{"date":"2025-07-30","close":298.27,"volume":540834,"signal":"BUY","psar":281.6987},{"date":"2025-07-31","close":288.4,"volume":640449,"signal":"BUY","psar":282.8111},{"date":"2025-08-01","close":284.91,"volume":567395,"signal":"SELL","psar":300.24},{"date":"2025-08-04","close":287.77,"volume":614596,"signal":"SELL","psar":299.8902},{"date":"2025-08-05","close":281.0,"volume":833126,"signal":"SELL","psar":299.5474},{"date":"2025-08-06","close":277.3,"volume":1016719,"signal":"SELL","psar":298.7939},{"date":"2025-08-07","close":303.55,"volume":1787833,"signal":null,"psar":276.46},{"date":"2025-08-08","close":307.1,"volume":1099682,"signal":null,"psar":276.46},{"date":"2025-08-11","close":304.84,"volume":725858,"signal":null,"psar":277.3868},{"date":"2025-08-12","close":309.63,"volume":723142,"signal":null,"psar":278.2951},{"date":"2025-08-13","close":308.68,"volume":804285,"signal":null,"psar":279.1852},{"date":"2025-08-14","close":315.78,"volume":763979,"signal":null,"psar":280.0575},{"date":"2025-08-15","close":321.27,"volume":617194,"signal":null,"psar":280.9123},{"date":"2025-08-18","close":323.07,"volume":457880,"signal":null,"psar":281.7501},{"date":"2025-08-19","close":327.48,"volume":534105,"signal":null,"psar":283.4335},{"date":"2025-08-20","close":333.0,"volume":618660,"signal":null,"psar":286.0889},{"date":"2025-08-21","close":327.85,"volume":458691,"signal":null,"psar":289.8745},{"date":"2025-08-22","close":330.77,"volume":499580,"signal":null,"psar":294.3051},{"date":"2025-08-25","close":329.0,"volume":517289,"signal":null,"psar":298.2926},{"date":"2025-08-26","close":331.83,"volume":493020,"signal":null,"psar":301.8813},{"date":"2025-08-27","close":334.35,"volume":516976,"signal":null,"psar":305.1112},{"date":"2025-08-28","close":337.6,"volume":458017,"signal":null,"psar":308.801},{"date":"2025-08-29","close":339.88,"volume":515186,"signal":null,"psar":312.8665},{"date":"2025-09-02","close":344.92,"volume":788603,"signal":null,"psar":317.3896},{"date":"2025-09-03","close":343.53,"volume":595483,"signal":null,"psar":323.2595},{"date":"2025-09-04","close":346.47,"volume":499731,"signal":null,"psar":328.0728},{"date":"2025-09-05","close":348.43,"volume":498478,"signal":null,"psar":332.0197},{"date":"2025-09-08","close":349.56,"volume":526583,"signal":null,"psar":335.2561},{"date":"2025-09-09","close":352.82,"volume":656739,"signal":null,"psar":337.91},{"date":"2025-09-10","close":337.61,"volume":800770,"signal":null,"psar":353.5},{"date":"2025-09-11","close":337.94,"volume":563757,"signal":null,"psar":353.5},{"date":"2025-09-12","close":341.78,"volume":472907,"signal":null,"psar":353.03},{"date":"2025-09-15","close":340.29,"volume":335535,"signal":null,"psar":352.5694},{"date":"2025-09-16","close":332.13,"volume":812075,"signal":null,"psar":352.118},{"date":"2025-09-17","close":322.22,"volume":1109004,"signal":null,"psar":351.1905},{"date":"2025-09-18","close":333.51,"volume":684781,"signal":null,"psar":348.9135},{"date":"2025-09-19","close":330.84,"volume":1028512,"signal":null,"psar":346.7731},{"date":"2025-09-22","close":335.12,"volume":431486,"signal":null,"psar":344.7611},{"date":"2025-09-23","close":327.8,"volume":435713,"signal":null,"psar":342.8698},{"date":"2025-09-24","close":326.97,"volume":576198,"signal":null,"psar":341.092},{"date":"2025-09-25","close":323.58,"volume":745502,"signal":null,"psar":339.4209},{"date":"2025-09-26","close":318.0,"volume":577406,"signal":null,"psar":337.2744},{"date":"2025-09-29","close":310.62,"volume":676500,"signal":null,"psar":335.2997},{"date":"2025-09-30","close":308.73,"volume":985771,"signal":null,"psar":332.6027},{"date":"2025-10-01","close":305.98,"volume":1140458,"signal":null,"psar":329.2472},{"date":"2025-10-02","close":312.21,"volume":545817,"signal":null,"psar":323.4754},{"date":"2025-10-03","close":309.115,"volume":651689,"signal":null,"psar":318.5116},{"date":"2025-10-06","close":311.69,"volume":538541,"signal":null,"psar":316.59},{"date":"2025-10-07","close":313.45,"volume":479941,"signal":null,"psar":316.59},{"date":"2025-10-08","close":315.49,"volume":465024,"signal":"BUY","psar":288.02},{"date":"2025-10-09","close":320.38,"volume":567335,"signal":"BUY","psar":288.6224},{"date":"2025-10-10","close":314.52,"volume":542993,"signal":"BUY","psar":290.0651},{"date":"2025-10-13","close":314.56,"volume":462698,"signal":"BUY","psar":291.4501},{"date":"2025-10-14","close":318.3,"volume":360823,"signal":"BUY","psar":292.7797},{"date":"2025-10-15","close":312.45,"volume":399724,"signal":"BUY","psar":294.0561},{"date":"2025-10-16","close":316.29,"volume":465991,"signal":"BUY","psar":295.2814},{"date":"2025-10-17","close":318.59,"volume":376883,"signal":"BUY","psar":296.4577},{"date":"2025-10-20","close":326.85,"volume":375974,"signal":"BUY","psar":297.587},{"date":"2025-10-21","close":328.97,"volume":441451,"signal":"BUY","psar":299.3446},{"date":"2025-10-22","close":329.22,"volume":557841,"signal":"BUY","psar":301.7946},{"date":"2025-10-23","close":323.46,"volume":411681,"signal":"BUY","psar":305.1412},{"date":"2025-10-24","close":320.91,"volume":297025,"signal":"BUY","psar":308.153},{"date":"2025-10-27","close":325.8,"volume":378344,"signal":"BUY","psar":310.8637},{"date":"2025-10-28","close":324.34,"volume":328723,"signal":"BUY","psar":313.3034},{"date":"2025-10-29","close":316.17,"volume":571113,"signal":null,"psar":335.26},{"date":"2025-10-30","close":311.95,"volume":403553,"signal":null,"psar":334.8532},{"date":"2025-10-31","close":313.01,"volume":543817,"signal":null,"psar":333.9191},{"date":"2025-11-03","close":318.77,"volume":634339,"signal":null,"psar":332.4398},{"date":"2025-11-04","close":320.27,"volume":605466,"signal":null,"psar":331.0493},{"date":"2025-11-05","close":314.44,"volume":854097,"signal":null,"psar":329.7423},{"date":"2025-11-06","close":323.4,"volume":1498288,"signal":null,"psar":308.84},{"date":"2025-11-07","close":319.82,"volume":677167,"signal":null,"psar":290.16},{"date":"2025-11-10","close":320.35,"volume":545020,"signal":null,"psar":290.16},{"date":"2025-11-11","close":326.28,"volume":476622,"signal":null,"psar":291.0568},{"date":"2025-11-12","close":336.84,"volume":606176,"signal":null,"psar":291.9357},{"date":"2025-11-13","close":332.67,"volume":550512,"signal":null,"psar":293.8386},{"date":"2025-11-14","close":332.7,"volume":405841,"signal":null,"psar":296.6701},{"date":"2025-11-17","close":328.02,"volume":512237,"signal":null,"psar":299.3317},{"date":"2025-11-18","close":333.47,"volume":654926,"signal":null,"psar":301.8336},{"date":"2025-11-19","close":346.36,"volume":978058,"signal":null,"psar":304.1854},{"date":"2025-11-20","close":312.89,"volume":1801408,"signal":null,"psar":307.709},{"date":"2025-11-21","close":331.17,"volume":1442987,"signal":null,"psar":312.06},{"date":"2025-11-24","close":337.53,"volume":1129395,"signal":null,"psar":312.06},{"date":"2025-11-25","close":328.85,"volume":884613,"signal":null,"psar":316.342},{"date":"2025-11-26","close":326.8,"volume":662066,"signal":null,"psar":320.1958},{"date":"2025-11-28","close":327.19,"volume":224657,"signal":null,"psar":323.6642},{"date":"2025-12-01","close":310.83,"volume":878707,"signal":"SELL","psar":354.88},{"date":"2025-12-02","close":309.0,"volume":759484,"signal":"SELL","psar":353.986},{"date":"2025-12-03","close":307.56,"volume":905108,"signal":"SELL","psar":352.0942},{"date":"2025-12-04","close":315.92,"volume":757061,"signal":"SELL","psar":349.1605},{"date":"2025-12-05","close":304.49,"volume":518069,"signal":"SELL","psar":346.4029},{"date":"2025-12-08","close":296.19,"volume":644331,"signal":"SELL","psar":342.9274},{"date":"2025-12-09","close":294.2,"volume":798293,"signal":"SELL","psar":338.1507},{"date":"2025-12-10","close":295.19,"volume":918557,"signal":"SELL","psar":332.8118},{"date":"2025-12-11","close":294.17,"volume":629459,"signal":"SELL","psar":327.206},{"date":"2025-12-12","close":295.7,"volume":576607,"signal":"SELL","psar":321.409},{"date":"2025-12-15","close":291.51,"volume":731473,"signal":"SELL","psar":316.5396},{"date":"2025-12-16","close":288.73,"volume":1029392,"signal":"SELL","psar":312.4492},{"date":"2025-12-17","close":289.57,"volume":697757,"signal":"SELL","psar":307.962},{"date":"2025-12-18","close":292.88,"volume":750260,"signal":"SELL","psar":304.2824},{"date":"2025-12-19","close":289.62,"volume":1179058,"signal":"SELL","psar":301.2652},{"date":"2025-12-22","close":291.57,"volume":627808,"signal":"SELL","psar":299.22},{"date":"2025-12-23","close":285.5,"volume":579908,"signal":"SELL","psar":297.114},{"date":"2025-12-24","close":288.82,"volume":294258,"signal":"SELL","psar":294.6952},{"date":"2025-12-26","close":288.63,"volume":310542,"signal":"SELL","psar":292.7602},{"date":"2025-12-29","close":287.36,"volume":580593,"signal":"SELL","psar":291.2121},{"date":"2025-12-30","close":287.03,"volume":322546,"signal":"SELL","psar":290.6},{"date":"2025-12-31","close":284.24,"volume":287648,"signal":"SELL","psar":290.6},{"date":"2026-01-02","close":282.92,"volume":456794,"signal":"SELL","psar":289.298},{"date":"2026-01-05","close":283.51,"volume":795107,"signal":"SELL","psar":287.4744},{"date":"2026-01-06","close":294.35,"volume":752605,"signal":null,"psar":278.79},{"date":"2026-01-07","close":299.17,"volume":573175,"signal":null,"psar":278.79},{"date":"2026-01-08","close":292.89,"volume":653453,"signal":null,"psar":279.6302},{"date":"2026-01-09","close":289.04,"volume":901965,"signal":null,"psar":280.4368},{"date":"2026-01-12","close":278.55,"volume":622874,"signal":"SELL","psar":299.795},{"date":"2026-01-13","close":278.17,"volume":667396,"signal":"SELL","psar":299.3511},{"date":"2026-01-14","close":282.89,"volume":794173,"signal":"SELL","psar":298.4583},{"date":"2026-01-15","close":286.49,"volume":733775,"signal":"SELL","psar":297.0568},{"date":"2026-01-16","close":287.7,"volume":664571,"signal":"SELL","psar":295.7394},{"date":"2026-01-20","close":284.25,"volume":588226,"signal":"SELL","psar":294.501},{"date":"2026-01-21","close":284.96,"volume":946769,"signal":"SELL","psar":293.3369},{"date":"2026-01-22","close":280.0,"volume":1305853,"signal":"SELL","psar":292.2427},{"date":"2026-01-23","close":271.6,"volume":1662653,"signal":"SELL","psar":291.2142},{"date":"2026-01-26","close":271.31,"volume":923592,"signal":"SELL","psar":289.1794},{"date":"2026-01-27","close":264.91,"volume":1479376,"signal":"SELL","psar":287.3075},{"date":"2026-01-28","close":258.2,"volume":1315299,"signal":"SELL","psar":284.7717},{"date":"2026-01-29","close":255.1,"volume":1300543,"signal":"SELL","psar":281.4775},{"date":"2026-01-30","close":255.81,"volume":1187746,"signal":"SELL","psar":277.6419},{"date":"2026-02-02","close":256.62,"volume":1069510,"signal":"SELL","psar":273.7056},{"date":"2026-02-03","close":251.22,"volume":976837,"signal":"SELL","psar":270.3991},{"date":"2026-02-04","close":251.24,"volume":1050907,"signal":"SELL","psar":266.6606},{"date":"2026-02-05","close":243.15,"volume":1339754,"signal":"SELL","psar":262.5565},{"date":"2026-02-06","close":241.93,"volume":1096385,"signal":"SELL","psar":258.5512},{"date":"2026-02-09","close":245.57,"volume":686354,"signal":"SELL","psar":255.1},{"date":"2026-02-10","close":252.41,"volume":1450028,"signal":null,"psar":240.03},{"date":"2026-02-11","close":250.85,"volume":726158,"signal":null,"psar":240.33},{"date":"2026-02-12","close":240.82,"volume":972769,"signal":"BUY","psar":240.6375},{"date":"2026-02-13","close":242.74,"volume":776046,"signal":"BUY","psar":240.78},{"date":"2026-02-17","close":246.34,"volume":1229100,"signal":"BUY","psar":240.78},{"date":"2026-02-18","close":258.07,"volume":2073700,"signal":"BUY","psar":241.0785},{"date":"2026-02-19","close":249.1,"volume":1416200,"signal":"BUY","psar":242.18},{"date":"2026-02-20","close":241.89,"volume":1396200,"signal":null,"psar":275.1},{"date":"2026-02-23","close":249.38,"volume":1597200,"signal":null,"psar":274.3384},{"date":"2026-02-24","close":245.25,"volume":1272500,"signal":null,"psar":273.592},{"date":"2026-02-25","close":248.12,"volume":880000,"signal":null,"psar":272.8606},{"date":"2026-02-26","close":251.5,"volume":1078200,"signal":null,"psar":272.1438},{"date":"2026-02-27","close":246.61,"volume":983800,"signal":null,"psar":271.4413},{"date":"2026-03-02","close":245.45,"volume":1179900,"signal":null,"psar":270.7529},{"date":"2026-03-03","close":241.84,"volume":938500,"signal":null,"psar":270.0782},{"date":"2026-03-04","close":242.89,"volume":1001000,"signal":null,"psar":268.7355},{"date":"2026-03-05","close":240.94,"volume":935700,"signal":null,"psar":267.4465},{"date":"2026-03-06","close":237.01,"volume":1226700,"signal":null,"psar":266.209},{"date":"2026-03-09","close":240.38,"volume":928165,"signal":null,"psar":264.2339},{"date":"2026-03-10","close":238.24,"volume":832240,"signal":null,"psar":262.3772},{"date":"2026-03-11","close":238.82,"volume":973900,"signal":null,"psar":260.632},{"date":"2026-03-12","close":236.07,"volume":850700,"signal":null,"psar":258.9915},{"date":"2026-03-13","close":219.84,"volume":2117000,"signal":null,"psar":257.4494},{"date":"2026-03-16","close":224.66,"volume":1119500,"signal":null,"psar":254.1726},{"date":"2026-03-17","close":230.49,"volume":1029800,"signal":null,"psar":251.158},{"date":"2026-03-18","close":230.28,"volume":743500,"signal":null,"psar":248.3846},{"date":"2026-03-19","close":228.63,"volume":740000,"signal":null,"psar":245.833},{"date":"2026-03-20","close":227.1,"volume":1062800,"signal":null,"psar":243.4856},{"date":"2026-03-23","close":227.08,"volume":671300,"signal":null,"psar":241.3259},{"date":"2026-03-24","close":225.5,"volume":546900,"signal":null,"psar":239.3391},{"date":"2026-03-25","close":216.0,"volume":1137600,"signal":null,"psar":237.5111},{"date":"2026-03-26","close":218.11,"volume":1040300,"signal":null,"psar":235.286},{"date":"2026-03-27","close":208.22,"volume":893000,"signal":null,"psar":233.2834},{"date":"2026-03-30","close":208.01,"volume":792700,"signal":null,"psar":230.2662},{"date":"2026-03-31","close":209.84,"volume":751600,"signal":null,"psar":226.7443},{"date":"2026-04-01","close":207.04,"volume":1169700,"signal":null,"psar":223.7155},{"date":"2026-04-02","close":204.31,"volume":886800,"signal":null,"psar":220.4154},{"date":"2026-04-06","close":203.5,"volume":1215200,"signal":null,"psar":217.1799},{"date":"2026-04-07","close":202.46,"volume":930600,"signal":null,"psar":214.5267},{"date":"2026-04-08","close":203.51,"volume":702800,"signal":null,"psar":211.2414},{"date":"2026-04-09","close":199.42,"volume":813800,"signal":null,"psar":209.0},{"date":"2026-04-10","close":196.93,"volume":729800,"signal":null,"psar":209.0},{"date":"2026-04-13","close":197.81,"volume":665600,"signal":null,"psar":206.256},{"date":"2026-04-14","close":201.49,"volume":733400,"signal":null,"psar":203.9268},{"date":"2026-04-15","close":202.5,"volume":802900,"signal":null,"psar":194.61},{"date":"2026-04-16","close":201.47,"volume":744800,"signal":null,"psar":194.8312},{"date":"2026-04-17","close":203.73,"volume":864800,"signal":"BUY","psar":195.048},{"date":"2026-04-20","close":200.87,"volume":587000,"signal":"BUY","psar":195.4841},{"date":"2026-04-21","close":192.33,"volume":788900,"signal":"SELL","psar":205.95},{"date":"2026-04-22","close":193.62,"volume":763800,"signal":"SELL","psar":205.6514},{"date":"2026-04-23","close":192.21,"volume":711800,"signal":"SELL","psar":205.3588},{"date":"2026-04-24","close":189.56,"volume":1116900,"signal":"SELL","psar":204.7296},{"date":"2026-04-27","close":188.31,"volume":646943,"signal":"SELL","psar":203.6208}]}